{
  "name": "@itwin/reality-capture-conversion",
  "entries": [
    {
      "date": "Thu, 07 Nov 2024 14:16:10 GMT",
      "version": "1.0.1",
      "tag": "@itwin/reality-capture-conversion_v1.0.1",
      "comments": {
        "none": [
          {
            "author": "110406974+dbiguenet@users.noreply.github.com",
            "package": "@itwin/reality-capture-conversion",
            "commit": "5396b814e5640bf45929cf9bf6e99a1961eb7752",
            "comment": "Fix contributing.md, readme.md and typescript dep version"
          }
        ]
      }
    },
    {
      "date": "Tue, 27 Feb 2024 10:50:42 GMT",
      "version": "1.0.1",
      "tag": "@itwin/reality-capture-conversion_v1.0.1",
      "comments": {
        "patch": [
          {
            "author": "110406974+dbiguenet@users.noreply.github.com",
            "package": "@itwin/reality-capture-conversion",
            "commit": "3d5aea6eda042a01d9e663fa52033970937f6564",
            "comment": "Fix RCS Bug (Merge option default value was true instead of false)"
          }
        ]
      }
    },
    {
      "date": "Mon, 12 Feb 2024 17:17:32 GMT",
      "version": "1.0.0",
      "tag": "@itwin/reality-capture-conversion_v1.0.0",
      "comments": {
        "major": [
          {
            "author": "110406974+dbiguenet@users.noreply.github.com",
            "package": "@itwin/reality-capture-conversion",
            "commit": "2b7049bc8c104a2434f5123b98670dfc45c7be6d",
            "comment": "Initial version 1.0.0"
          }
        ]
      }
    }
  ]
}
